<?xml version="1.0" encoding="UTF-8"?>
<skill xmlns="http://www.masagroup.net/directia/schemas/bm" name="commander.skills.CoordinationManager" source-version="1.0.0">
  <parameters>
    <parameter name="enititesFromEchelon">
      <description>Les unités de cet echelon qui vont être coordonées.</description>
      <type>
        <list>
          <class name="world_concepts.Commanding"/>
        </list>
      </type>
    </parameter>
    <parameter name="distance">
      <description>La distance à ne pas dépasser  entre les échelons ou au sein d'un échelon</description>
      <type>
        <simple name="numeric"/>
      </type>
    </parameter>
    <parameter name="progressionInAOR">
      <type>
        <list>
          <simple name="numeric"/>
        </list>
      </type>
    </parameter>
  </parameters>
  <modifiers/>
  <links/>
  <resources/>
</skill>