<?xml version="1.0" encoding="UTF-8"?>
<class xmlns="http://www.masagroup.net/directia/schemas/bm" name="company.combat.tasks.knowledges.MonitorEffect" source-version="1.0.0" extends="commander.tasks.knowledges.CompanyTask">
  <methods>
    <method name="getPositions">
      <return>
        <type>
          <list>
            <class name="directia.core.Object"/>
          </list>
        </type>
      </return>
    </method>
    <method name="getEntities">
      <return>
        <type>
          <list>
            <class name="directia.core.Object"/>
          </list>
        </type>
      </return>
    </method>
    <method name="getDirection">
      <return>
        <type>
          <list>
            <class name="directia.core.Object"/>
          </list>
        </type>
      </return>
    </method>
    <method name="getScoutObjectives">
      <return>
        <type>
          <list>
            <class name="directia.core.Object"/>
          </list>
        </type>
      </return>
    </method>
    <method name="getObjectives">
      <return>
        <type>
          <list>
            <class name="directia.core.Object"/>
          </list>
        </type>
      </return>
    </method>
  </methods>
</class>