<?xml version="1.0" encoding="UTF-8"?>
<skill xmlns="http://www.masagroup.net/directia/schemas/bm" name="sword.military.platoon.skills.actions.MoveAndTakePosition" source-version="1.0.0">
    <description>Déplacement puis poste sur l'élement passé en paramètre. Utilisé par tous les skills de haut niveau.</description>
    <parameters>
        <parameter name="entity">
            <description>L'élément que l'on veut rejoindre et occuper</description>
            <type>
                <class name="sword.military.knowledge.decisional.Positionable"/>
            </type>
        </parameter>
        <parameter name="pathType">
            <description>Le type de d'itineraire à emprunter est défini numéruiquement par une énumération. Une valeur de 0 correspond au type d'initéraire &quot;mouvement&quot;, qui favorise les routes ou tout type de terrain permettant d'aller &quot;au plus vite&quot;. &#xD;
Les valeurs sont:&#xD;
eTypeItiMouvement = 0&#xD;
eTypeItiReconnaissance = 1&#xD;
eTypeItiInfiltration = 2&#xD;
eTypeItiAttaque = 3&#xD;
eTypeItiRepli = 4&#xD;
eTypeItiAppui = 5&#xD;
eTypeItiDeminage = 6&#xD;
eTypeItiLogistique = 7</description>
            <type>
                <simple name="numeric"/>
            </type>
            <default>
                <number>0.0</number>
            </default>
        </parameter>
    </parameters>
    <body-type>
        <class name="sword.military.knowledge.Mountable"/>
    </body-type>
    <links>
        <link name="dismount" skill="sword.military.platoon.skills.actions.Dismount"/>
        <link name="mount" skill="sword.military.platoon.skills.actions.Mount"/>
    </links>
    <resources>
        <resource name="sword.military.platoon.resources.MoveCapacity" variable="move">
            <description>La mise en oeuvre des capacités de mouvement.</description>
        </resource>
        <resource name="sword.military.platoon.resources.MountCapacity" variable="mount">
            <description>$$$ TEMP SWORD</description>
        </resource>
    </resources>
    <feedbacks>
        <feedback name="done">
            <argument name="element">
                <type>
                    <class name="sword.military.knowledge.decisional.Positionable"/>
                </type>
            </argument>
            <argument name="reason">
                <type>
                     <simple name="string"/>
                </type>
            </argument>
        </feedback>
    </feedbacks>
</skill>