<?xml version="1.0" encoding="UTF-8"?>
<skill xmlns="http://www.masagroup.net/directia/schemas/bm" name="france.military.platoon.combat.support.rens.skills.primitives.ActivateRadar" source-version="1.0.0">
    <parameters>
        <parameter name="area">
            <description>Zone</description>
            <type>
                <class name="world_elements.Area"/>
            </type>
        </parameter>
        <parameter name="typeRadar">
            <type>
                <simple name="numeric"/>
            </type>
        </parameter>
    </parameters>
    <resources>
        <resource name="agent.resources.RadarCapacity" variable="radar">
            <description>La mise en oeuvre des équipements radar</description>
        </resource>
    </resources>
</skill>