<?xml version="1.0" encoding="UTF-8"?>
<fires xmlns:xsi="http://www.w3.org/2001/XMLSchema-instance" model-version="4.6.0" xsi:noNamespaceSchemaLocation="schemas/4.3.1/physical/Fires.xsd">
  <cell-size value="1000"/>
  <fire decrease-rate="10" increase-rate="20" initial-heat="0" max-heat="10000" name="Class A">
    <extinguisher-agents>
      <extinguisher-agent agent="h2o" heat-decrease-rate="1"/>
    </extinguisher-agents>
    <weather-effects>
      <weather-effect heat-decrease-rate="0" weather="PasDePrecipitation"/>
      <weather-effect heat-decrease-rate="0" weather="TempeteDeSable"/>
      <weather-effect heat-decrease-rate="0" weather="Brouillard"/>
      <weather-effect heat-decrease-rate="0" weather="Crachin"/>
      <weather-effect heat-decrease-rate="0" weather="Pluie"/>
      <weather-effect heat-decrease-rate="0" weather="Neige"/>
      <weather-effect heat-decrease-rate="0" weather="Fumigene"/>
    </weather-effects>
    <injuries>
      <injury percentage="0.2" type="u1"/>
      <injury percentage="0.2" type="u2"/>
      <injury percentage="0.2" type="u3"/>
      <injury percentage="0.2" type="ue"/>
      <injury percentage="0.2" type="dead"/>
    </injuries>
    <urban-modifiers>
      <urban-modifier material-type="Bois" value="0"/>
      <urban-modifier material-type="Beton" value="0"/>
      <urban-modifier material-type="Brique" value="0"/>
      <urban-modifier material-type="Metal" value="0"/>
      <urban-modifier material-type="Torchis" value="0"/>
      <urban-modifier material-type="Prefabrique" value="0"/>
      <urban-modifier material-type="Vegetation" value="0"/>
    </urban-modifiers>
    <surfaces>
      <surface ignition-threshold="300" max-combustion-energy="1000" type="error"/>
      <surface ignition-threshold="200" max-combustion-energy="1000" type="error"/>
      <surface ignition-threshold="100" max-combustion-energy="1000" type="error"/>
      <surface ignition-threshold="1000" max-combustion-energy="1000" type="error"/>
      <surface ignition-threshold="10000" max-combustion-energy="1000" type="dune"/>
      <surface ignition-threshold="500" max-combustion-energy="1000" type="error"/>
      <surface ignition-threshold="100000" max-combustion-energy="1000" type="error"/>
      <surface ignition-threshold="100000" max-combustion-energy="1000" type="error"/>
      <surface ignition-threshold="0" max-combustion-energy="0" type="error"/>
      <surface ignition-threshold="0" max-combustion-energy="0" type="error"/>
      <surface ignition-threshold="0" max-combustion-energy="0" type="error"/>
      <surface ignition-threshold="0" max-combustion-energy="0" type="error"/>
      <surface ignition-threshold="0" max-combustion-energy="0" type="error"/>
      <surface ignition-threshold="0" max-combustion-energy="0" type="error"/>
      <surface ignition-threshold="0" max-combustion-energy="0" type="error"/>
      <surface ignition-threshold="0" max-combustion-energy="0" type="error"/>
      <surface ignition-threshold="0" max-combustion-energy="0" type="error"/>
      <surface ignition-threshold="0" max-combustion-energy="0" type="error"/>
      <surface ignition-threshold="0" max-combustion-energy="0" type="error"/>
      <surface ignition-threshold="0" max-combustion-energy="0" type="error"/>
      <surface ignition-threshold="0" max-combustion-energy="0" type="error"/>
      <surface ignition-threshold="0" max-combustion-energy="0" type="error"/>
      <surface ignition-threshold="0" max-combustion-energy="0" type="error"/>
      <surface ignition-threshold="0" max-combustion-energy="0" type="error"/>
      <surface ignition-threshold="0" max-combustion-energy="0" type="error"/>
      <surface ignition-threshold="0" max-combustion-energy="0" type="error"/>
      <surface ignition-threshold="300" max-combustion-energy="1000" type="error"/>
      <surface ignition-threshold="0" max-combustion-energy="0" type="error"/>
    </surfaces>
  </fire>
  <fire decrease-rate="10" increase-rate="20" initial-heat="0" max-heat="10000" name="Class B">
    <extinguisher-agents>
      <extinguisher-agent agent="h2o" heat-decrease-rate="1"/>
    </extinguisher-agents>
    <weather-effects>
      <weather-effect heat-decrease-rate="0" weather="PasDePrecipitation"/>
      <weather-effect heat-decrease-rate="0" weather="TempeteDeSable"/>
      <weather-effect heat-decrease-rate="0" weather="Brouillard"/>
      <weather-effect heat-decrease-rate="0" weather="Crachin"/>
      <weather-effect heat-decrease-rate="0" weather="Pluie"/>
      <weather-effect heat-decrease-rate="0" weather="Neige"/>
      <weather-effect heat-decrease-rate="0" weather="Fumigene"/>
    </weather-effects>
    <injuries>
      <injury percentage="0.2" type="u1"/>
      <injury percentage="0.2" type="u2"/>
      <injury percentage="0.2" type="u3"/>
      <injury percentage="0.2" type="ue"/>
      <injury percentage="0.2" type="dead"/>
    </injuries>
    <urban-modifiers>
      <urban-modifier material-type="Bois" value="0"/>
      <urban-modifier material-type="Beton" value="0"/>
      <urban-modifier material-type="Brique" value="0"/>
      <urban-modifier material-type="Metal" value="0"/>
      <urban-modifier material-type="Torchis" value="0"/>
      <urban-modifier material-type="Prefabrique" value="0"/>
      <urban-modifier material-type="Vegetation" value="0"/>
    </urban-modifiers>
    <surfaces>
      <surface ignition-threshold="200" max-combustion-energy="1000" type="error"/>
      <surface ignition-threshold="100" max-combustion-energy="1000" type="error"/>
      <surface ignition-threshold="200" max-combustion-energy="1000" type="error"/>
      <surface ignition-threshold="300" max-combustion-energy="1000" type="error"/>
      <surface ignition-threshold="400" max-combustion-energy="1000" type="dune"/>
      <surface ignition-threshold="500" max-combustion-energy="1000" type="error"/>
      <surface ignition-threshold="600" max-combustion-energy="1000" type="error"/>
      <surface ignition-threshold="700" max-combustion-energy="1000" type="error"/>
      <surface ignition-threshold="0" max-combustion-energy="0" type="error"/>
      <surface ignition-threshold="0" max-combustion-energy="0" type="error"/>
      <surface ignition-threshold="0" max-combustion-energy="0" type="error"/>
      <surface ignition-threshold="0" max-combustion-energy="0" type="error"/>
      <surface ignition-threshold="0" max-combustion-energy="0" type="error"/>
      <surface ignition-threshold="0" max-combustion-energy="0" type="error"/>
      <surface ignition-threshold="0" max-combustion-energy="0" type="error"/>
      <surface ignition-threshold="0" max-combustion-energy="0" type="error"/>
      <surface ignition-threshold="0" max-combustion-energy="0" type="error"/>
      <surface ignition-threshold="0" max-combustion-energy="0" type="error"/>
      <surface ignition-threshold="0" max-combustion-energy="0" type="error"/>
      <surface ignition-threshold="0" max-combustion-energy="0" type="error"/>
      <surface ignition-threshold="0" max-combustion-energy="0" type="error"/>
      <surface ignition-threshold="0" max-combustion-energy="0" type="error"/>
      <surface ignition-threshold="0" max-combustion-energy="0" type="error"/>
      <surface ignition-threshold="0" max-combustion-energy="0" type="error"/>
      <surface ignition-threshold="0" max-combustion-energy="0" type="error"/>
      <surface ignition-threshold="0" max-combustion-energy="0" type="error"/>
      <surface ignition-threshold="800" max-combustion-energy="1000" type="error"/>
      <surface ignition-threshold="0" max-combustion-energy="0" type="error"/>
    </surfaces>
  </fire>
  <fire decrease-rate="10" increase-rate="20" initial-heat="0" max-heat="10000" name="Class C">
    <extinguisher-agents>
      <extinguisher-agent agent="h2o" heat-decrease-rate="1"/>
    </extinguisher-agents>
    <weather-effects>
      <weather-effect heat-decrease-rate="0" weather="PasDePrecipitation"/>
      <weather-effect heat-decrease-rate="0" weather="TempeteDeSable"/>
      <weather-effect heat-decrease-rate="0" weather="Brouillard"/>
      <weather-effect heat-decrease-rate="0" weather="Crachin"/>
      <weather-effect heat-decrease-rate="0" weather="Pluie"/>
      <weather-effect heat-decrease-rate="0" weather="Neige"/>
      <weather-effect heat-decrease-rate="0" weather="Fumigene"/>
    </weather-effects>
    <injuries>
      <injury percentage="0.2" type="u1"/>
      <injury percentage="0.2" type="u2"/>
      <injury percentage="0.2" type="u3"/>
      <injury percentage="0.2" type="ue"/>
      <injury percentage="0.2" type="dead"/>
    </injuries>
    <urban-modifiers>
      <urban-modifier material-type="Bois" value="0"/>
      <urban-modifier material-type="Beton" value="0"/>
      <urban-modifier material-type="Brique" value="0"/>
      <urban-modifier material-type="Metal" value="0"/>
      <urban-modifier material-type="Torchis" value="0"/>
      <urban-modifier material-type="Prefabrique" value="0"/>
      <urban-modifier material-type="Vegetation" value="0"/>
    </urban-modifiers>
    <surfaces>
      <surface ignition-threshold="100" max-combustion-energy="1000" type="error"/>
      <surface ignition-threshold="200" max-combustion-energy="1000" type="error"/>
      <surface ignition-threshold="300" max-combustion-energy="1000" type="error"/>
      <surface ignition-threshold="400" max-combustion-energy="1000" type="error"/>
      <surface ignition-threshold="500" max-combustion-energy="1000" type="dune"/>
      <surface ignition-threshold="600" max-combustion-energy="1000" type="error"/>
      <surface ignition-threshold="700" max-combustion-energy="1000" type="error"/>
      <surface ignition-threshold="800" max-combustion-energy="1000" type="error"/>
      <surface ignition-threshold="0" max-combustion-energy="0" type="error"/>
      <surface ignition-threshold="0" max-combustion-energy="0" type="error"/>
      <surface ignition-threshold="0" max-combustion-energy="0" type="error"/>
      <surface ignition-threshold="0" max-combustion-energy="0" type="error"/>
      <surface ignition-threshold="0" max-combustion-energy="0" type="error"/>
      <surface ignition-threshold="0" max-combustion-energy="0" type="error"/>
      <surface ignition-threshold="0" max-combustion-energy="0" type="error"/>
      <surface ignition-threshold="0" max-combustion-energy="0" type="error"/>
      <surface ignition-threshold="0" max-combustion-energy="0" type="error"/>
      <surface ignition-threshold="0" max-combustion-energy="0" type="error"/>
      <surface ignition-threshold="0" max-combustion-energy="0" type="error"/>
      <surface ignition-threshold="0" max-combustion-energy="0" type="error"/>
      <surface ignition-threshold="0" max-combustion-energy="0" type="error"/>
      <surface ignition-threshold="0" max-combustion-energy="0" type="error"/>
      <surface ignition-threshold="0" max-combustion-energy="0" type="error"/>
      <surface ignition-threshold="0" max-combustion-energy="0" type="error"/>
      <surface ignition-threshold="0" max-combustion-energy="0" type="error"/>
      <surface ignition-threshold="0" max-combustion-energy="0" type="error"/>
      <surface ignition-threshold="900" max-combustion-energy="1000" type="error"/>
      <surface ignition-threshold="0" max-combustion-energy="0" type="error"/>
    </surfaces>
  </fire>
  <fire decrease-rate="10" increase-rate="20" initial-heat="0" max-heat="10000" name="Class D">
    <extinguisher-agents>
      <extinguisher-agent agent="h2o" heat-decrease-rate="1"/>
    </extinguisher-agents>
    <weather-effects>
      <weather-effect heat-decrease-rate="0" weather="PasDePrecipitation"/>
      <weather-effect heat-decrease-rate="0" weather="TempeteDeSable"/>
      <weather-effect heat-decrease-rate="0" weather="Brouillard"/>
      <weather-effect heat-decrease-rate="0" weather="Crachin"/>
      <weather-effect heat-decrease-rate="0" weather="Pluie"/>
      <weather-effect heat-decrease-rate="0" weather="Neige"/>
      <weather-effect heat-decrease-rate="0" weather="Fumigene"/>
    </weather-effects>
    <injuries>
      <injury percentage="0.2" type="u1"/>
      <injury percentage="0.2" type="u2"/>
      <injury percentage="0.2" type="u3"/>
      <injury percentage="0.2" type="ue"/>
      <injury percentage="0.2" type="dead"/>
    </injuries>
    <urban-modifiers>
      <urban-modifier material-type="Bois" value="0"/>
      <urban-modifier material-type="Beton" value="0"/>
      <urban-modifier material-type="Brique" value="0"/>
      <urban-modifier material-type="Metal" value="0"/>
      <urban-modifier material-type="Torchis" value="0"/>
      <urban-modifier material-type="Prefabrique" value="0"/>
      <urban-modifier material-type="Vegetation" value="0"/>
    </urban-modifiers>
    <surfaces>
      <surface ignition-threshold="100" max-combustion-energy="1000" type="error"/>
      <surface ignition-threshold="100" max-combustion-energy="1000" type="error"/>
      <surface ignition-threshold="100" max-combustion-energy="1000" type="error"/>
      <surface ignition-threshold="100" max-combustion-energy="1000" type="error"/>
      <surface ignition-threshold="100" max-combustion-energy="1000" type="dune"/>
      <surface ignition-threshold="100" max-combustion-energy="1000" type="error"/>
      <surface ignition-threshold="100" max-combustion-energy="1000" type="error"/>
      <surface ignition-threshold="100" max-combustion-energy="1000" type="error"/>
      <surface ignition-threshold="0" max-combustion-energy="0" type="error"/>
      <surface ignition-threshold="0" max-combustion-energy="0" type="error"/>
      <surface ignition-threshold="0" max-combustion-energy="0" type="error"/>
      <surface ignition-threshold="0" max-combustion-energy="0" type="error"/>
      <surface ignition-threshold="0" max-combustion-energy="0" type="error"/>
      <surface ignition-threshold="0" max-combustion-energy="0" type="error"/>
      <surface ignition-threshold="0" max-combustion-energy="0" type="error"/>
      <surface ignition-threshold="0" max-combustion-energy="0" type="error"/>
      <surface ignition-threshold="0" max-combustion-energy="0" type="error"/>
      <surface ignition-threshold="0" max-combustion-energy="0" type="error"/>
      <surface ignition-threshold="0" max-combustion-energy="0" type="error"/>
      <surface ignition-threshold="0" max-combustion-energy="0" type="error"/>
      <surface ignition-threshold="0" max-combustion-energy="0" type="error"/>
      <surface ignition-threshold="0" max-combustion-energy="0" type="error"/>
      <surface ignition-threshold="0" max-combustion-energy="0" type="error"/>
      <surface ignition-threshold="0" max-combustion-energy="0" type="error"/>
      <surface ignition-threshold="0" max-combustion-energy="0" type="error"/>
      <surface ignition-threshold="0" max-combustion-energy="0" type="error"/>
      <surface ignition-threshold="100" max-combustion-energy="1000" type="error"/>
      <surface ignition-threshold="0" max-combustion-energy="0" type="error"/>
    </surfaces>
  </fire>
</fires><!-- signature="0358971735" -->
