<?xml version="1.0" encoding="UTF-8" standalone="no" ?>
<orbat model-version="4.8.3" xmlns:xsi="http://www.w3.org/2001/XMLSchema-instance" xsi:noNamespaceSchemaLocation="schemas/4.3.3/exercise/orbat.xsd">
  <parties>
    <party color="0x647dff" id="1" name="Bleu" type="friend">
      <objects>
        <object id="5" name="Destruction de pont" type="bridge destruction">
          <shape type="point">
            <points>
              <point>29TNF3346854523</point>
            </points>
          </shape>
          <attributes>
            <obstacle activated="true" type="preliminary"/>
            <construction completion="1"/>
          </attributes>
        </object>
        <object id="14" name="zone nbc [14]" type="nbc zone">
          <shape type="polygone">
            <points>
              <point>29TNF3237555224</point>
              <point>29TNF3250854731</point>
              <point>29TNF3364854863</point>
              <point>29TNF3358055358</point>
            </points>
          </shape>
          <attributes>
            <construction completion="1"/>
            <nbc-agents danger="0" state="liquid">
              <nbc-agent type="Biologique"/>
            </nbc-agents>
          </attributes>
        </object>
        <object id="82" name="poste controle [82]" type="checkpoint">
          <shape type="point">
            <points>
              <point>29TNF3248956102</point>
            </points>
          </shape>
          <attributes>
            <construction completion="1"/>
          </attributes>
        </object>
      </objects>
      <tactical>
        <formation color="0x647dff" id="72" level="ii" name="32">
          <automat color="0x647dff" engaged="false" id="73" knowledge-group="18" name="SGTIA PIA [73]" type="SGTIA PIA">
            <unit color="0x647dff" command-post="true" id="74" name="PC SGTIA" position="29TNF3150657591" type="PC SGTIA"/>
            <unit color="0x647dff" command-post="false" id="75" name="PIA Dominante ABC" position="29TNF3186157035" type="PIA Dominante ABC"/>
            <unit color="0x647dff" command-post="false" id="76" name="PIA Dominante INF" position="29TNF3151156593" type="PIA Dominante INF"/>
            <unit color="0x647dff" command-post="false" id="77" name="PIA Dominante Reco" position="29TNF3100857090" type="PIA Dominante Reco"/>
            <unit color="0x647dff" command-post="false" id="78" name="ABC . Patrouille EI 12,7" position="29TNF3200657593" type="ABC . Patrouille EI 12,7"/>
          </automat>
        </formation>
      </tactical>
      <communication>
        <knowledge-group id="18" name="Groupe de connaissance [18]" type="Standard"/>
      </communication>
      <populations>
        <population attitude="calme" id="4" name="Foule standard [4]" position="29TNF3396552863" type="Foule standard">
          <composition contaminated="0" dead="0" healthy="1000" wounded="0"/>
          <adhesions>
            <adhesion party="1" value="0"/>
            <adhesion party="33" value="0"/>
          </adhesions>
        </population>
        <population attitude="calme" id="58" name="Foule armée [58]" position="29TNF3749256202" type="Foule armée">
          <composition contaminated="0" dead="0" healthy="1000" wounded="0"/>
          <armed-individuals value="0.5"/>
          <repartition children="0.35" female="0.35" male="0.65"/>
          <adhesions>
            <adhesion party="1" value="0"/>
            <adhesion party="33" value="0"/>
          </adhesions>
        </population>
      </populations>
      <inhabitants/>
      <logistics/>
    </party>
    <party color="0xff0000" id="33" name="Rouge" type="friend">
      <objects>
        <object id="80" name="bouchon mines [80]" type="mines">
          <shape type="point">
            <points>
              <point>29TNF3526755169</point>
            </points>
          </shape>
          <attributes>
            <obstacle activated="false" type="reserved">
              <activation-time value="600"/>
              <activity-time value="0"/>
            </obstacle>
            <construction completion="1"/>
            <activity-time value="0"/>
          </attributes>
        </object>
        <object id="81" name="zone brouillage [81]" type="jamming area">
          <shape type="polygone">
            <points>
              <point>29TNF3373158585</point>
              <point>29TNF3483658590</point>
              <point>29TNF3465057996</point>
              <point>29TNF3372358171</point>
            </points>
          </shape>
          <attributes>
            <construction completion="1"/>
          </attributes>
        </object>
      </objects>
      <tactical>
        <formation color="0xff0000" id="65" level="ii" name="31">
          <automat color="0xff0000" engaged="true" id="66" knowledge-group="36" name="INF . Compagnie CBT AMX 10 P [66]" type="INF . Compagnie CBT AMX 10 P">
            <unit color="0xff0000" command-post="true" id="67" name="INF . Section CDT CIE quaternaire AMX10P" position="29TNF3401560331" type="INF . Section CDT CIE quaternaire AMX10P"/>
            <unit color="0xff0000" command-post="false" id="68" name="INF . Section CBT AMX10P CDS OFF" position="29TNF3293956967" type="INF . Section CBT AMX10P CDS OFF"/>
            <unit color="0xff0000" command-post="false" id="69" name="INF . Section CBT AMX10P CDS OFF" position="29TNF3402059334" type="INF . Section CBT AMX10P CDS OFF"/>
            <unit color="0xff0000" command-post="false" id="70" name="INF . Section CBT AMX10P CDS OFF" position="29TNF3290856802" type="INF . Section CBT AMX10P CDS OFF"/>
            <unit color="0xff0000" command-post="false" id="71" name="INF . Section CBT AMX10P CDS SOFF" position="29TNF3451660334" type="INF . Section CBT AMX10P CDS SOFF"/>
          </automat>
        </formation>
      </tactical>
      <communication>
        <knowledge-group id="36" name="Groupe de connaissance [36]" type="Standard"/>
      </communication>
      <populations>
        <population attitude="calme" id="50" name="Foule standard [50]" position="29TNF3572257797" type="Foule standard">
          <composition contaminated="0" dead="0" healthy="1000" wounded="0"/>
          <adhesions>
            <adhesion party="1" value="0"/>
            <adhesion party="33" value="0"/>
          </adhesions>
        </population>
      </populations>
      <inhabitants/>
      <logistics/>
    </party>
  </parties>
  <diplomacy>
    <party id="1">
      <relationship diplomacy="enemy" party="33"/>
    </party>
    <party id="33">
      <relationship diplomacy="enemy" party="1"/>
    </party>
  </diplomacy>
</orbat>
<!-- signature="1156144647" -->