<?xml version="1.0" encoding="UTF-8"?>
<class xmlns="http://www.masagroup.net/directia/schemas/bm" name="world.classes.UrbanBlock" source-version="1.0.0" extends="world.classes.LocalizedElement">
    <realizes>world.interfaces.Installation</realizes>
    <methods>
        <method name="getPosition">
            <return name="simPosition">
                <type>
                    <any/>
                </type>
            </return>
        </method>
        <method name="getPositions">
            <return>
                <type>
                    <list>
                        <any/>
                    </list>
                </type>
            </return>
        </method>
        <method name="isDamaged" abstract="false">
            <description>Returns 'true' if this element is damaged, 'false' otherwise.&#xD;
&#xD;
This implementation  returns 'true' if the structural state is equal to 0%. This means that this urban block is considered damaged if it is destroyed.</description>
            <return>
                <type>
                    <simple name="boolean"/>
                </type>
            </return>
        </method>
        <method name="isReached" abstract="false">
            <description>Returns true if this object has a proximity of 100% and should be considered as being reached by the agent, false otherwise.&#xD;
&#xD;
This implementation returns 'true' if at least one  flow of the crowd has reached the border of the urban block.</description>
            <return>
                <type>
                    <simple name="boolean"/>
                </type>
            </return>
        </method>
        <method name="damageIt" abstract="false">
            <description>To damage this element. Returns 'true' upon action completion.&#xD;
The quatity of damage is here used as a percentage.</description>
            <argument name="quantityOfDamage">
                <description>The quantity of damage to apply onto the installation.</description>
                <type>
                    <simple name="numeric"/>
                </type>
            </argument>
            <return>
                <type>
                    <simple name="boolean"/>
                </type>
            </return>
        </method>
    </methods>
</class>